odoo/addons/base_generate_code/README.rst
odoo/addons/base_generate_code/__init__.py
odoo/addons/base_generate_code/__manifest__.py
odoo/addons/base_generate_code/i18n/base_generate_code.pot
odoo/addons/base_generate_code/i18n/es_AR.po
odoo/addons/base_generate_code/i18n/fr.po
odoo/addons/base_generate_code/i18n/hr.po
odoo/addons/base_generate_code/models/__init__.py
odoo/addons/base_generate_code/models/code_format_mixin.py
odoo/addons/base_generate_code/readme/CONTRIBUTORS.rst
odoo/addons/base_generate_code/readme/DESCRIPTION.rst
odoo/addons/base_generate_code/readme/USAGE.rst
odoo/addons/base_generate_code/security/ir.model.access.csv
odoo/addons/base_generate_code/static/description/icon.png
odoo/addons/base_generate_code/static/description/index.html
odoo/addons/base_generate_code/tests/__init__.py
odoo/addons/base_generate_code/tests/fake_models.py
odoo/addons/base_generate_code/tests/test_code_format_mixin.py
odoo14_addon_base_generate_code-14.0.1.1.1.dist-info/METADATA
odoo14_addon_base_generate_code-14.0.1.1.1.dist-info/WHEEL
odoo14_addon_base_generate_code-14.0.1.1.1.dist-info/top_level.txt
odoo14_addon_base_generate_code-14.0.1.1.1.dist-info/RECORD
